<annotation>
  <folder>VOC2007</folder>
  <filename>mix_37.jpg</filename>
  <size>
    <width>160</width>
    <height>160</height>
    <depth>3</depth>
  </size>
  <object>
    <name>pitaya</name>
    <difficult>0</difficult>
    <bndbox>
      <xmin>82.61255041305928</xmin>
      <ymin>22.56264049715703</ymin>
      <xmax>125.61255041305928</xmax>
      <ymax>50.562640497157034</ymax>
    </bndbox>
  </object>
  <object>
    <name>apple</name>
    <difficult>0</difficult>
    <bndbox>
      <xmin>51.61255041305928</xmin>
      <ymin>23.56264049715703</ymin>
      <xmax>78.61255041305928</xmax>
      <ymax>53.562640497157034</ymax>
    </bndbox>
  </object>
  <object>
    <name>pitaya</name>
    <difficult>0</difficult>
    <bndbox>
      <xmin>12.612550413059296</xmin>
      <ymin>55.562640497157034</ymin>
      <xmax>73.61255041305928</xmax>
      <ymax>95.56264049715703</ymax>
    </bndbox>
  </object>
</annotation>
