<annotation>
  <folder>VOC2007</folder>
  <filename>mix_46.jpg</filename>
  <size>
    <width>171</width>
    <height>171</height>
    <depth>3</depth>
  </size>
  <object>
    <name>pitaya</name>
    <difficult>0</difficult>
    <bndbox>
      <xmin>99.84663314902025</xmin>
      <ymin>19.767870193063217</ymin>
      <xmax>134.84663314902025</xmax>
      <ymax>56.76787019306322</ymax>
    </bndbox>
  </object>
  <object>
    <name>pitaya</name>
    <difficult>0</difficult>
    <bndbox>
      <xmin>63.84663314902025</xmin>
      <ymin>39.76787019306322</ymin>
      <xmax>104.84663314902025</xmax>
      <ymax>81.76787019306322</ymax>
    </bndbox>
  </object>
  <object>
    <name>pitaya</name>
    <difficult>0</difficult>
    <bndbox>
      <xmin>33.84663314902025</xmin>
      <ymin>43.76787019306322</ymin>
      <xmax>70.84663314902025</xmax>
      <ymax>66.76787019306322</ymax>
    </bndbox>
  </object>
</annotation>
